alibabacloud_polardbai20251013/__init__.py
alibabacloud_polardbai20251013/client.py
alibabacloud_polardbai20251013/models/__init__.py
alibabacloud_polardbai20251013/models/_chat_biconfig_create_request.py
alibabacloud_polardbai20251013/models/_chat_biconfig_create_response.py
alibabacloud_polardbai20251013/models/_chat_biconfig_create_response_body.py
alibabacloud_polardbai20251013/models/_chat_biconfig_delete_entry_request.py
alibabacloud_polardbai20251013/models/_chat_biconfig_delete_entry_response.py
alibabacloud_polardbai20251013/models/_chat_biconfig_delete_entry_response_body.py
alibabacloud_polardbai20251013/models/_chat_biconfig_delete_request.py
alibabacloud_polardbai20251013/models/_chat_biconfig_delete_response.py
alibabacloud_polardbai20251013/models/_chat_biconfig_delete_response_body.py
alibabacloud_polardbai20251013/models/_chat_biconfig_query_entries_request.py
alibabacloud_polardbai20251013/models/_chat_biconfig_query_entries_response.py
alibabacloud_polardbai20251013/models/_chat_biconfig_query_entries_response_body.py
alibabacloud_polardbai20251013/models/_chat_biconfig_query_tables_request.py
alibabacloud_polardbai20251013/models/_chat_biconfig_query_tables_response.py
alibabacloud_polardbai20251013/models/_chat_biconfig_query_tables_response_body.py
alibabacloud_polardbai20251013/models/_chat_biconfig_update_entry_request.py
alibabacloud_polardbai20251013/models/_chat_biconfig_update_entry_response.py
alibabacloud_polardbai20251013/models/_chat_biconfig_update_entry_response_body.py
alibabacloud_polardbai20251013/models/_chat_bifile_template_download_request.py
alibabacloud_polardbai20251013/models/_chat_bifile_template_download_response.py
alibabacloud_polardbai20251013/models/_chat_bifile_template_download_response_body.py
alibabacloud_polardbai20251013/models/_chat_bifile_upload_callback_request.py
alibabacloud_polardbai20251013/models/_chat_bifile_upload_callback_response.py
alibabacloud_polardbai20251013-1.2.0.dist-info/LICENSE
alibabacloud_polardbai20251013-1.2.0.dist-info/METADATA
alibabacloud_polardbai20251013-1.2.0.dist-info/WHEEL
alibabacloud_polardbai20251013-1.2.0.dist-info/top_level.txt
alibabacloud_polardbai20251013-1.2.0.dist-info/RECORD
